mkdocs_ringcentral/__init__.py
mkdocs_ringcentral/base.html
mkdocs_ringcentral/footer.html
mkdocs_ringcentral/logo_beta.svg
mkdocs_ringcentral/main-nav.html
mkdocs_ringcentral/mkdocs_theme.yml
mkdocs_ringcentral/side-nav.html
mkdocs_ringcentral/css/ringcentral.css
mkdocs_ringcentral/img/footer_rclogo.png
mkdocs_ringcentral/img/logo_beta.svg
mkdocs_ringcentral/img/nav-secondary-engage-arrow.svg
mkdocs_ringcentral/img/nav-secondary-office-arrow.svg
mkdocs_ringcentral/js/rc.js
mkdocs_ringcentral-0.1.28.dist-info/METADATA
mkdocs_ringcentral-0.1.28.dist-info/WHEEL
mkdocs_ringcentral-0.1.28.dist-info/entry_points.txt
mkdocs_ringcentral-0.1.28.dist-info/top_level.txt
mkdocs_ringcentral-0.1.28.dist-info/RECORD
