Metadata-Version: 2.1
Name: mkdocs-ringcentral
Version: 0.1.28
Summary: RingCentral theme for MkDocs
Home-page: https://github.com/byrnereese/mkdocs-ringcentral/
Author: Byrne Reese
Author-email: byrne.reese@ringcentral.com
Requires-Python: >=3.0
Requires-Dist: mkdocs (>=1.1)
Requires-Dist: mkdocs-ringcentral-api-index (>=0.1.6)
Requires-Dist: mkdocs-moonstone (>=0.2.0)
Requires-Dist: mdx-include (>=0.4.1)
